trello2md/__init__.py
trello2md/__main__.py
trello2md/api.py
trello2md/cli.py
trello2md-0.5.0.dist-info/LICENSE.txt
trello2md-0.5.0.dist-info/METADATA
trello2md-0.5.0.dist-info/WHEEL
trello2md-0.5.0.dist-info/entry_points.txt
trello2md-0.5.0.dist-info/top_level.txt
trello2md-0.5.0.dist-info/RECORD
