Metadata-Version: 2.1
Name: trello2md
Version: 0.5.0
Summary: Export Trello boards and cards to Markdown
Home-page: https://github.com/bhrutledge/trello2md
Author: Brian Rutledge
Author-email: brian@bhrutledge.com
License: MIT
Platform: UNKNOWN
Classifier: Development Status :: 3 - Alpha
Classifier: Environment :: Console
Classifier: License :: OSI Approved :: MIT License
Classifier: Programming Language :: Python :: 3
Classifier: Programming Language :: Python :: 3 :: Only
Classifier: Programming Language :: Python :: 3.8
Classifier: Topic :: Utilities
Requires-Python: >=3.8
Requires-Dist: docopt
Requires-Dist: py-trello (>=0.16)
